zoobot/__init__.py
zoobot/pytorch/__init__.py
zoobot/pytorch/manchester.py
zoobot/pytorch/datasets/__init__.py
zoobot/pytorch/estimators/__init__.py
zoobot/pytorch/estimators/cuda_check.py
zoobot/pytorch/estimators/custom_layers.py
zoobot/pytorch/estimators/define_model.py
zoobot/pytorch/estimators/efficientnet_custom.py
zoobot/pytorch/predictions/__init__.py
zoobot/pytorch/predictions/predict_on_catalog.py
zoobot/pytorch/training/__init__.py
zoobot/pytorch/training/finetune.py
zoobot/pytorch/training/losses.py
zoobot/pytorch/training/representations.py
zoobot/pytorch/training/schedulers.py
zoobot/pytorch/training/temp.py
zoobot/pytorch/training/tensorboard_writers.py
zoobot/pytorch/training/train_with_pytorch_lightning.py
zoobot/shared/__init__.py
zoobot/shared/benchmark_datasets.py
zoobot/shared/compress_representations.py
zoobot/shared/label_metadata.py
zoobot/shared/load_predictions.py
zoobot/shared/save_predictions.py
zoobot/shared/schemas.py
zoobot/shared/stats.py
zoobot-2.9.0.dist-info/licenses/LICENSE
zoobot-2.9.0.dist-info/METADATA
zoobot-2.9.0.dist-info/WHEEL
zoobot-2.9.0.dist-info/top_level.txt
zoobot-2.9.0.dist-info/RECORD
