Metadata-Version: 2.4
Name: zoobot
Version: 2.9.0
Summary: Galaxy morphology classifiers
Home-page: https://github.com/mwalmsley/zoobot
Author: Mike Walmsley
Author-email: walmsleymk1@gmail.com
Classifier: Programming Language :: Python :: 3
Classifier: License :: OSI Approved :: GNU General Public License (GPL)
Classifier: Operating System :: OS Independent
Classifier: Development Status :: 4 - Beta
Classifier: Environment :: GPU :: NVIDIA CUDA
Requires-Python: >=3.9
License-File: LICENSE
Requires-Dist: h5py
Requires-Dist: tqdm
Requires-Dist: pillow
Requires-Dist: numpy
Requires-Dist: pandas
Requires-Dist: scipy
Requires-Dist: astropy
Requires-Dist: scikit-learn>=1.0.2
Requires-Dist: matplotlib
Requires-Dist: pyarrow
Requires-Dist: wandb
Requires-Dist: webdataset
Requires-Dist: huggingface_hub
Requires-Dist: setuptools
Requires-Dist: galaxy-datasets>=0.0.25
Provides-Extra: pytorch
Requires-Dist: torch>=2.7.0; extra == "pytorch"
Requires-Dist: torchvision; extra == "pytorch"
Requires-Dist: torchaudio; extra == "pytorch"
Requires-Dist: torchmetrics; extra == "pytorch"
Requires-Dist: lightning>=2.2.5; extra == "pytorch"
Requires-Dist: litmodels; extra == "pytorch"
Requires-Dist: timm>=1.0.15; extra == "pytorch"
Provides-Extra: pytorch-colab
Requires-Dist: lightning>=2.2.5; extra == "pytorch-colab"
Provides-Extra: utilities
Requires-Dist: seaborn; extra == "utilities"
Requires-Dist: boto3; extra == "utilities"
Requires-Dist: python-dateutil==2.8.1; extra == "utilities"
Provides-Extra: docs
Requires-Dist: Sphinx; extra == "docs"
Requires-Dist: sphinxcontrib-napoleon; extra == "docs"
Requires-Dist: furo; extra == "docs"
Requires-Dist: docutils<0.18; extra == "docs"
Requires-Dist: sphinxemoji; extra == "docs"
Dynamic: author
Dynamic: author-email
Dynamic: classifier
Dynamic: description
Dynamic: description-content-type
Dynamic: home-page
Dynamic: license-file
Dynamic: provides-extra
Dynamic: requires-dist
Dynamic: requires-python
Dynamic: summary
